coinapi_rest_v1/__init__.py
coinapi_rest_v1/examples.py
coinapi_rest_v1/restapi.py
coinapi_rest_v1-1.4.dist-info/LICENSE
coinapi_rest_v1-1.4.dist-info/METADATA
coinapi_rest_v1-1.4.dist-info/WHEEL
coinapi_rest_v1-1.4.dist-info/top_level.txt
coinapi_rest_v1-1.4.dist-info/RECORD
