Metadata-Version: 2.2
Name: coinapi.rest.v1
Version: 1.4
Summary: SDKs for CoinAPI
Home-page: https://docs.coinapi.io/
Author: Tomasz Przybysz
Author-email: tom.przybysz@gmail.com
Classifier: Programming Language :: Python :: 3
Classifier: License :: OSI Approved :: MIT License
Classifier: Operating System :: OS Independent
Requires-Python: >=3.0
License-File: LICENSE
Dynamic: author
Dynamic: author-email
Dynamic: classifier
Dynamic: description
Dynamic: description-content-type
Dynamic: home-page
Dynamic: requires-python
Dynamic: summary
